sqlite_dao_ext/__init__.py
sqlite_dao_ext/kv_dao/__init__.py
sqlite_dao_ext/kv_dao/kv_dao.py
sqlite_dao_ext/kv_dao/kv_data.py
sqlite_dao_ext/kv_dao/sqlite_kv_dao.py
sqlite_dao_ext/sqlite_client/__init__.py
sqlite_dao_ext/sqlite_client/sqlite_client.py
sqlite_dao_ext/sqlite_client/sqlite_query.py
sqlite_dao_ext/sqlite_dao/__init__.py
sqlite_dao_ext/sqlite_dao/sqlite_dao.py
sqlite_dao_ext/sqlite_dao/sqlite_data_object.py
sqlite_dao_ext/sqlite_dao/sqlite_query_generator.py
sqlite_dao_ext/utils/__init__.py
sqlite_dao_ext/utils/dataclass_utils.py
sqlite_dao_ext-0.1.8.dist-info/METADATA
sqlite_dao_ext-0.1.8.dist-info/WHEEL
sqlite_dao_ext-0.1.8.dist-info/top_level.txt
sqlite_dao_ext-0.1.8.dist-info/RECORD
