Metadata-Version: 2.1
Name: sqlite-dao-ext
Version: 0.1.8
Summary: Sqlite3 Dao
Classifier: Programming Language :: Python :: 3
Classifier: License :: OSI Approved :: MIT License
Classifier: Operating System :: OS Independent
Requires-Python: >=3.9
Requires-Dist: dataclasses
Requires-Dist: typing
